LICENSE
NOTICE
README.md
pyproject.toml
strictdoc/__init__.py
strictdoc/backend/__init__.py
strictdoc/backend/excel/__init__.py
strictdoc/backend/excel/excel_import.py
strictdoc/backend/excel/export/__init__.py
strictdoc/backend/excel/export/excel_generator.py
strictdoc/backend/excel/import_/__init__.py
strictdoc/backend/excel/import_/excel_sheet_proxy.py
strictdoc/backend/excel/import_/excel_to_sdoc_converter.py
strictdoc/backend/reqif/__init__.py
strictdoc/backend/reqif/reqif_export.py
strictdoc/backend/reqif/reqif_import.py
strictdoc/backend/reqif/reqif_reader.py
strictdoc/backend/reqif/sdoc_reqif_fields.py
strictdoc/backend/reqif/p01_sdoc/__init__.py
strictdoc/backend/reqif/p01_sdoc/reqif_to_sdoc_converter.py
strictdoc/backend/reqif/p01_sdoc/sdoc_to_reqif_converter.py
strictdoc/backend/sdoc/__init__.py
strictdoc/backend/sdoc/constants.py
strictdoc/backend/sdoc/document_reference.py
strictdoc/backend/sdoc/error_handling.py
strictdoc/backend/sdoc/free_text_reader.py
strictdoc/backend/sdoc/grammar_reader.py
strictdoc/backend/sdoc/pickle_cache.py
strictdoc/backend/sdoc/processor.py
strictdoc/backend/sdoc/reader.py
strictdoc/backend/sdoc/writer.py
strictdoc/backend/sdoc/errors/__init__.py
strictdoc/backend/sdoc/errors/document_tree_error.py
strictdoc/backend/sdoc/grammar/__init__.py
strictdoc/backend/sdoc/grammar/grammar.py
strictdoc/backend/sdoc/grammar/grammar_builder.py
strictdoc/backend/sdoc/grammar/grammar_grammar.py
strictdoc/backend/sdoc/grammar/type_system.py
strictdoc/backend/sdoc/models/__init__.py
strictdoc/backend/sdoc/models/anchor.py
strictdoc/backend/sdoc/models/constants.py
strictdoc/backend/sdoc/models/document.py
strictdoc/backend/sdoc/models/document_config.py
strictdoc/backend/sdoc/models/document_from_file.py
strictdoc/backend/sdoc/models/document_grammar.py
strictdoc/backend/sdoc/models/document_view.py
strictdoc/backend/sdoc/models/free_text.py
strictdoc/backend/sdoc/models/grammar_element.py
strictdoc/backend/sdoc/models/inline_link.py
strictdoc-0.16.3.dist-info/METADATA
strictdoc-0.16.3.dist-info/WHEEL
strictdoc-0.16.3.dist-info/entry_points.txt
strictdoc-0.16.3.dist-info/licenses/LICENSE
strictdoc-0.16.3.dist-info/licenses/NOTICE
strictdoc-0.16.3.dist-info/RECORD
